dictionary/__init__.py
dictionary/dictionary.py
sarp_ulas_kaya_cs453_hwork_1-2.1.0.dist-info/METADATA
sarp_ulas_kaya_cs453_hwork_1-2.1.0.dist-info/WHEEL
sarp_ulas_kaya_cs453_hwork_1-2.1.0.dist-info/top_level.txt
sarp_ulas_kaya_cs453_hwork_1-2.1.0.dist-info/RECORD
