Metadata-Version: 2.1
Name: sarp-ulas-kaya-cs453-hwork-1
Version: 2.1.0
Summary: UNKNOWN
Author: Sarp Ulas Kaya
License: UNKNOWN
Platform: UNKNOWN
Requires-Python: >=3.8
Requires-Dist: requests (>=2.23.0)
